fastapitableau/__init__.py
fastapitableau/applications.py
fastapitableau/exception_handlers.py
fastapitableau/logger.py
fastapitableau/middleware.py
fastapitableau/openapi.py
fastapitableau/pages.py
fastapitableau/routing.py
fastapitableau/rstudio_connect.py
fastapitableau/user_guide.py
fastapitableau/utils.py
fastapitableau/statics/css/styles.css
fastapitableau/templates/index.html
fastapitableau/templates/param_table.html
fastapitableau/templates/setup_tableau.html
fastapitableau/templates/tableau_usage.html
fastapitableau/templates/user_guide.html
fastapitableau-1.3.0.dist-info/METADATA
fastapitableau-1.3.0.dist-info/WHEEL
fastapitableau-1.3.0.dist-info/top_level.txt
fastapitableau-1.3.0.dist-info/zip-safe
fastapitableau-1.3.0.dist-info/RECORD
