Metadata-Version: 2.1
Name: fastapitableau
Version: 1.3.0
Summary: A Python package for writing FastAPI apps that you can call from Tableau.
Home-page: https://github.com/rstudio/fastapitableau
Author: Toph Allen, James Blair, Bill Sager
Author-email: toph@rstudio.com
License: MIT
Classifier: Environment :: Web Environment
Classifier: Intended Audience :: Developers
Classifier: License :: OSI Approved :: BSD License
Classifier: Operating System :: OS Independent
Classifier: Programming Language :: Python
Classifier: Programming Language :: Python :: 3.7
Classifier: Topic :: Internet :: WWW/HTTP :: Dynamic Content
Classifier: Topic :: Software Development :: Libraries :: Python Modules
Requires-Python: >=3.7
Requires-Dist: fastapi>=0.103.1
Requires-Dist: aiofiles
Requires-Dist: commonmark
Requires-Dist: requests
Requires-Dist: jinja2
Provides-Extra: test
Requires-Dist: pytest; extra == "test"
